{
  "fullscreen": 1,
  "use_photos": 0,
  "screen_width": 800,
  "screen_height": 480,
  "bg_color":[0,0,0],
  "clock_font": "quicksand",
  "time_face_percent": 45,
  "date_face_percent": 10,
  "weather_face_percent": 8,
  "day_text_color": [0,0,0],
  "night_text_color": [255,255,255],
  "time_format": "%H:%M:%S",
  "date_format": "%A, %B %d",
  "temperature_units": "celsius",
  "api_key": "Your OpenWeather API key",
  "queries_per_minute": 2,
  "day_color": [135,206,235],
  "night_color": [12,20,69],
  "cloud_speed": 0.1,
  "minimum_percent_of_last_cloud": 5,
  "raindrop_speed": 15,
  "snowflake_speed": 1
}
